reagent/__init__.py
reagent/debug_on_error.py
reagent/json_serialize.py
reagent/parameters.py
reagent/parameters_seq2slate.py
reagent/tensorboardX.py
reagent/torch_utils.py
reagent/types.py
reagent/evaluation/__init__.py
reagent/evaluation/cpe.py
reagent/evaluation/doubly_robust_estimator.py
reagent/evaluation/evaluation_data_page.py
reagent/evaluation/evaluator.py
reagent/evaluation/ranking_listwise_evaluator.py
reagent/evaluation/ranking_policy_gradient_evaluator.py
reagent/evaluation/reward_net_evaluator.py
reagent/evaluation/sequential_doubly_robust_estimator.py
reagent/evaluation/weighted_sequential_doubly_robust_estimator.py
reagent/evaluation/world_model_evaluator.py
reagent/gym/__init__.py
reagent/gym/types.py
reagent/gym/utils.py
reagent/gym/agents/__init__.py
reagent/gym/agents/agent.py
reagent/gym/agents/post_step.py
reagent/gym/envs/__init__.py
reagent/gym/envs/env_factory.py
reagent/gym/envs/recsim.py
reagent/gym/envs/simple_minigrid.py
reagent/gym/envs/utils.py
reagent/gym/policies/__init__.py
reagent/gym/policies/policy.py
reagent/gym/policies/predictor_policies.py
reagent/gym/policies/random_policies.py
reagent/gym/policies/samplers/__init__.py
reagent/gym/policies/samplers/continuous_sampler.py
reagent/gym/policies/samplers/discrete_sampler.py
reagent/gym/policies/samplers/top_k_sampler.py
reagent/gym/policies/scorers/__init__.py
reagent/gym/policies/scorers/continuous_scorer.py
reagent/gym/policies/scorers/discrete_scorer.py
reagent/gym/policies/scorers/slate_q_scorer.py
reagent/gym/preprocessors/__init__.py
reagent/gym/preprocessors/default_preprocessors.py
reagent/gym/preprocessors/default_serving_preprocessors.py
reagent/gym/preprocessors/replay_buffer_inserters.py
reagent/gym/preprocessors/trainer_preprocessor.py
reagent/gym/runners/__init__.py
reagent/gym/runners/gymrunner.py
reagent/gym/tests/__init__.py
reagent/gym/tests/test_gym.py
reagent/gym/tests/test_gym_offline.py
reagent/gym/tests/test_linear_dynamics.py
reagent-0.1.dist-info/LICENSE
reagent-0.1.dist-info/METADATA
reagent-0.1.dist-info/WHEEL
reagent-0.1.dist-info/top_level.txt
reagent-0.1.dist-info/RECORD
