Metadata-Version: 2.1
Name: reagent
Version: 0.1
Summary: Facebook RL
Home-page: https://github.com/facebookresearch/ReAgent
Author: Facebook
License: BSD 3-Clause License
Platform: UNKNOWN
Requires-Python: >=3.7
Requires-Dist: click (>=7.0)
Requires-Dist: cloudpickle (~=1.2.0)
Requires-Dist: numpy (>=1.17.2)
Requires-Dist: pandas (>=1.0.3)
Requires-Dist: pydantic (>=1.4)
Requires-Dist: torch
Requires-Dist: tqdm (>=4.46.0)
Requires-Dist: petastorm (>=0.9.0)
Requires-Dist: parameterized (>=0.7.4)
Requires-Dist: pyspark (>=2.4.5)
Requires-Dist: ruamel.yaml (>=0.15.99)
Requires-Dist: scipy (>=1.3.1)
Requires-Dist: tensorboard (>=1.14)
Requires-Dist: scikit-learn (>=0.20.0)
Requires-Dist: xgboost (==0.90)
Provides-Extra: gym
Requires-Dist: gym[atari,box2d,classic_control] ; extra == 'gym'
Requires-Dist: gym-minigrid ; extra == 'gym'
Requires-Dist: recsim-no-tf ; extra == 'gym'
Provides-Extra: test
Requires-Dist: coverage (>=5.1) ; extra == 'test'
Requires-Dist: pytest-xdist (==1.30.0) ; extra == 'test'
Requires-Dist: pytest (==5.3) ; extra == 'test'
Requires-Dist: spark-testing-base (==0.10.0) ; extra == 'test'
Requires-Dist: pytest-cov ; extra == 'test'
